{
  "definitions": {
    "v1beta1BackupScheduleRequest": {
      "properties": {
        "auth_secret_name": {
          "maxLength": 63,
          "pattern": "^[a-z0-9](?:[a-z0-9\\-]{0,61}[a-z0-9])?$",
          "type": "string"
        },
        "bucket_name": {
          "maxLength": 63,
          "pattern": "^[a-z0-9](?:[a-z0-9\\-]{0,61}[a-z0-9])?$",
          "type": "string"
        },
        "cluster": {
          "type": "string"
        },
        "credential_uid": {
          "type": "string"
        },
        "schedule_cron_expr": {
          "type": "string"
        },
        "snapshot_name": {
          "maxLength": 63,
          "pattern": "^[a-z0-9](?:[a-z0-9\\-]{0,61}[a-z0-9])?$",
          "type": "string"
        },
        "uid": {
          "type": "string"
        }
      },
      "title": "Next Id: 13",
      "type": "object"
    },
    "v1beta1BackupUnscheduleRequest": {
      "properties": {
        "cluster": {
          "type": "string"
        },
        "uid": {
          "type": "string"
        }
      },
      "title": "Next Id: 3",
      "type": "object"
    },
    "v1beta1SnapshotDescribeRequest": {
      "properties": {
        "cluster": {
          "type": "string"
        },
        "phid": {
          "type": "string"
        },
        "uid": {
          "type": "string"
        }
      },
      "title": "Next Id: 4",
      "type": "object"
    },
    "v1beta1SnapshotListRequest": {
      "properties": {
        "cluster": {
          "type": "string"
        },
        "uid": {
          "type": "string"
        }
      },
      "title": "Next Id: 3",
      "type": "object"
    },
    "v1beta1SnapshotRestoreRequest": {
      "properties": {
        "auth_secret_name": {
          "maxLength": 63,
          "pattern": "^[a-z0-9](?:[a-z0-9\\-]{0,61}[a-z0-9])?$",
          "type": "string"
        },
        "cluster": {
          "type": "string"
        },
        "snapshot_phid": {
          "type": "string"
        },
        "uid": {
          "type": "string"
        }
      },
      "title": "Next Id: 19",
      "type": "object"
    }
  }
}